wmill_pg/__init__.py
wmill_pg/client.py
wmill_pg/py.typed
wmill_pg-1.623.0.dist-info/METADATA
wmill_pg-1.623.0.dist-info/WHEEL
wmill_pg-1.623.0.dist-info/RECORD
